deepresearch_flow/__init__.py
deepresearch_flow/__main__.py
deepresearch_flow/cli.py
deepresearch_flow/paper/__init__.py
deepresearch_flow/paper/cli.py
deepresearch_flow/paper/config.py
deepresearch_flow/paper/db.py
deepresearch_flow/paper/db_ops.py
deepresearch_flow/paper/extract.py
deepresearch_flow/paper/llm.py
deepresearch_flow/paper/prompts.py
deepresearch_flow/paper/render.py
deepresearch_flow/paper/schema.py
deepresearch_flow/paper/template_registry.py
deepresearch_flow/paper/utils.py
deepresearch_flow/paper/prompt_templates/__init__.py
deepresearch_flow/paper/prompt_templates/deep_read_phi_system.j2
deepresearch_flow/paper/prompt_templates/deep_read_phi_user.j2
deepresearch_flow/paper/prompt_templates/deep_read_system.j2
deepresearch_flow/paper/prompt_templates/deep_read_user.j2
deepresearch_flow/paper/prompt_templates/eight_questions_phi_system.j2
deepresearch_flow/paper/prompt_templates/eight_questions_phi_user.j2
deepresearch_flow/paper/prompt_templates/eight_questions_system.j2
deepresearch_flow/paper/prompt_templates/eight_questions_user.j2
deepresearch_flow/paper/prompt_templates/simple_phi_system.j2
deepresearch_flow/paper/prompt_templates/simple_phi_user.j2
deepresearch_flow/paper/prompt_templates/simple_system.j2
deepresearch_flow/paper/prompt_templates/simple_user.j2
deepresearch_flow/paper/prompt_templates/three_pass_system.j2
deepresearch_flow/paper/prompt_templates/three_pass_user.j2
deepresearch_flow/paper/providers/__init__.py
deepresearch_flow/paper/providers/azure_openai.py
deepresearch_flow/paper/providers/base.py
deepresearch_flow/paper/providers/claude.py
deepresearch_flow/paper/providers/dashscope.py
deepresearch_flow/paper/providers/gemini.py
deepresearch_flow/paper/providers/ollama.py
deepresearch_flow/paper/providers/openai_compatible.py
deepresearch_flow/paper/schemas/__init__.py
deepresearch_flow/paper/schemas/deep_read_phi_schema.json
deepresearch_flow/paper/schemas/deep_read_schema.json
deepresearch_flow-0.6.1.dist-info/licenses/LICENSE
deepresearch_flow-0.6.1.dist-info/METADATA
deepresearch_flow-0.6.1.dist-info/WHEEL
deepresearch_flow-0.6.1.dist-info/entry_points.txt
deepresearch_flow-0.6.1.dist-info/top_level.txt
deepresearch_flow-0.6.1.dist-info/RECORD
