Metadata-Version: 2.4
Name: deepresearch-flow
Version: 0.6.1
Summary: Workflow tools for paper extraction, review, and research automation.
Author-email: DengQi <dengqi935@gmail.com>
License: MIT License
Project-URL: Homepage, https://github.com/nerdneilsfield/ai-deepresearch-flow
Project-URL: Repository, https://github.com/nerdneilsfield/ai-deepresearch-flow
Project-URL: Issues, https://github.com/nerdneilsfield/ai-deepresearch-flow/issues
Keywords: research,papers,pdf,ocr,llm,workflow
Classifier: Development Status :: 3 - Alpha
Classifier: Intended Audience :: Science/Research
Classifier: License :: OSI Approved :: MIT License
Classifier: Programming Language :: Python :: 3
Classifier: Programming Language :: Python :: 3 :: Only
Classifier: Topic :: Scientific/Engineering :: Information Analysis
Requires-Python: >=3.12
License-File: LICENSE
Requires-Dist: anthropic>=0.77.0
Requires-Dist: click>=8.1.7
Requires-Dist: coloredlogs>=15.0.1
Requires-Dist: dashscope>=1.25.10
Requires-Dist: google-auth>=2.48.0
Requires-Dist: google-genai>=1.60.0
Requires-Dist: httpx>=0.27.0
Requires-Dist: jinja2>=3.1.3
Requires-Dist: json-repair>=0.55.1
Requires-Dist: jsonschema>=4.26.0
Requires-Dist: markdown-it-py>=3.0.0
Requires-Dist: mdit-py-plugins>=0.4.0
Requires-Dist: pypdf>=6.6.2
Requires-Dist: pylatexenc>=2.10
Requires-Dist: pybtex>=0.24.0
Requires-Dist: rich>=14.3.1
Requires-Dist: rumdl>=0.1.6
Requires-Dist: starlette>=0.52.1
Requires-Dist: tqdm>=4.66.4
Requires-Dist: uvicorn>=0.27.1
Dynamic: license-file
